odoo8_addon_purchase_requisition_transport_multi_address-8.0.1.0.0-py2.7-nspkg.pth
odoo_addons/purchase_requisition_transport_multi_address/__openerp__.py
odoo_addons/purchase_requisition_transport_multi_address/__init__.py
odoo_addons/purchase_requisition_transport_multi_address/README.rst
odoo_addons/purchase_requisition_transport_multi_address/view/purchase_requisition.xml
odoo_addons/purchase_requisition_transport_multi_address/i18n/purchase_requisition_transport_multi_address.pot
odoo_addons/purchase_requisition_transport_multi_address/model/purchase_requisition.py
odoo_addons/purchase_requisition_transport_multi_address/model/__init__.py
odoo_addons/purchase_requisition_transport_multi_address/static/description/icon.png
odoo8_addon_purchase_requisition_transport_multi_address-8.0.1.0.0.dist-info/top_level.txt
odoo8_addon_purchase_requisition_transport_multi_address-8.0.1.0.0.dist-info/WHEEL
odoo8_addon_purchase_requisition_transport_multi_address-8.0.1.0.0.dist-info/RECORD
odoo8_addon_purchase_requisition_transport_multi_address-8.0.1.0.0.dist-info/metadata.json
odoo8_addon_purchase_requisition_transport_multi_address-8.0.1.0.0.dist-info/DESCRIPTION.rst
odoo8_addon_purchase_requisition_transport_multi_address-8.0.1.0.0.dist-info/METADATA
odoo8_addon_purchase_requisition_transport_multi_address-8.0.1.0.0.dist-info/namespace_packages.txt
